traceflow/__init__.py
traceflow/__main__.py
traceflow/packet.py
traceflow/printer.py
traceflow/socket_handler.py
traceflow-0.4.dist-info/LICENSE
traceflow-0.4.dist-info/METADATA
traceflow-0.4.dist-info/WHEEL
traceflow-0.4.dist-info/entry_points.txt
traceflow-0.4.dist-info/top_level.txt
traceflow-0.4.dist-info/RECORD
