Metadata-Version: 2.1
Name: traceflow
Version: 0.4
Summary: Python version of traceroute which is path aware
Home-page: https://github.com/rucarrol/traceflow
Author: Ruairi Carroll
Author-email: ruairi.carroll@gmail.com
License: UNKNOWN
Platform: UNKNOWN
Classifier: Programming Language :: Python :: 3
Classifier: Development Status :: 4 - Beta
Classifier: Environment :: Console
Classifier: License :: OSI Approved :: BSD License
Classifier: Operating System :: OS Independent
Requires-Python: >=3.5
